LICENSE
MANIFEST.in
README.md
requirements.txt
setup.cfg
setup.py
test-requirements.txt
test_fileload.py
test_swiftlm_check.py
test_swiftlm_detect.py
doc/source/Makefile
doc/source/access_log_metrics.rst
doc/source/aggregate_scout.rst
doc/source/conf.py
doc/source/index.rst
doc/source/monasca_plugin.rst
doc/source/standalone_scripts.rst
doc/source/swiftlm_scan_metrics.rst
doc/source/swiftlm_uptime_mon_metrics.rst
doc/source/test_runner.rst
swiftlm/__init__.py
swiftlm.egg-info/PKG-INFO
swiftlm.egg-info/SOURCES.txt
swiftlm.egg-info/dependency_links.txt
swiftlm.egg-info/entry_points.txt
swiftlm.egg-info/not-zip-safe
swiftlm.egg-info/requires.txt
swiftlm.egg-info/top_level.txt
swiftlm/cli/__init__.py
swiftlm/cli/aggregate.py
swiftlm/cli/drive_provision.py
swiftlm/cli/jahmoncli.py
swiftlm/cli/log_tailer.py
swiftlm/cli/memcached.py
swiftlm/cli/probe_100_continue.py
swiftlm/cli/runner.py
swiftlm/cli/scout.py
swiftlm/cli/supervisor.py
swiftlm/cli/uptime_mon.py
swiftlm/generic_hardware/__init__.py
swiftlm/hp_hardware/__init__.py
swiftlm/hp_hardware/ssacli.py
swiftlm/monasca/__init__.py
swiftlm/monasca/check_plugins/__init__.py
swiftlm/monasca/check_plugins/swiftlm_check.py
swiftlm/monasca/detect_plugins/__init__.py
swiftlm/monasca/detect_plugins/swiftlm_detect.py
swiftlm/rings/__init__.py
swiftlm/rings/ardana_model.py
swiftlm/rings/ring_builder.py
swiftlm/rings/ring_model.py
swiftlm/swift/__init__.py
swiftlm/swift/drive_audit.py
swiftlm/swift/file_ownership.py
swiftlm/swift/replication.py
swiftlm/swift/swift_services.py
swiftlm/systems/__init__.py
swiftlm/systems/check_mounts.py
swiftlm/systems/connectivity.py
swiftlm/systems/ntp.py
swiftlm/systems/system.py
swiftlm/utils/__init__.py
swiftlm/utils/drivedata.py
swiftlm/utils/jahmonapi.py
swiftlm/utils/log_tailer.py
swiftlm/utils/metricdata.py
swiftlm/utils/ringdata.py
swiftlm/utils/scout.py
swiftlm/utils/status.py
swiftlm/utils/utility.py
swiftlm/utils/values.py
tests/__init__.py
tests/cli/test_probe_100_continue.py
tests/cli/test_supervisor.py
tests/cli/test_uptime_mon.py
tests/data/__init__.py
tests/data/drive_audit_data.py
tests/data/drive_data.py
tests/data/ring_standard.py
tests/data/rings_data.py
tests/data/rings_ringspecs.py
