Metadata-Version: 1.0
Name: swiftlm
Version: 3.1.0
Summary: Lifecycle management for Openstack Swift systems
Home-page: https://github.com/ArdanaCLM
Author: SUSE LLC
Author-email: ardana@googlegroups.com
License: Apache 2.0
Keywords: Openstack Swift
Platform: UNKNOWN
